Maniverse.cpython-310-x86_64-linux-gnu.so
maniverse.libs/libgcc_s-0cd532bd.so.1
maniverse.libs/libstdc++-5d72f927.so.6.0.33
maniverse-2.0.0.dist-info/METADATA
maniverse-2.0.0.dist-info/WHEEL
maniverse-2.0.0.dist-info/top_level.txt
maniverse-2.0.0.dist-info/RECORD
maniverse-2.0.0.dist-info/licenses/LICENSE
maniverse-2.0.0.dist-info/sboms/auditwheel.cdx.json
