Metadata-Version: 2.4
Name: Maniverse
Version: 2.0.0
Summary: Numerical optimization on manifolds
Home-page: https://github.com/FreemanTheMaverick/Maniverse.git
Author: FreemanTheMaverick
Classifier: Programming Language :: Python :: 3
License-File: LICENSE
Dynamic: author
Dynamic: classifier
Dynamic: description
Dynamic: description-content-type
Dynamic: home-page
Dynamic: license-file
Dynamic: summary
